gocept.patch_keyreferences-0.1-py3.8-nspkg.pth
gocept/patch_keyreferences/__init__.py
gocept/patch_keyreferences/configure.zcml
gocept/patch_keyreferences/ftesting.zcml
gocept/patch_keyreferences/patch.py
gocept/patch_keyreferences/regression.rst
gocept/patch_keyreferences/testing.py
gocept/patch_keyreferences/tests.py
gocept.patch_keyreferences-0.1.dist-info/LICENSE.txt
gocept.patch_keyreferences-0.1.dist-info/METADATA
gocept.patch_keyreferences-0.1.dist-info/WHEEL
gocept.patch_keyreferences-0.1.dist-info/namespace_packages.txt
gocept.patch_keyreferences-0.1.dist-info/top_level.txt
gocept.patch_keyreferences-0.1.dist-info/RECORD
