Metadata-Version: 2.1
Name: gocept.patch-keyreferences
Version: 0.1
Summary: Fix for the comparison of security wrapped keyreferences.
Home-page: https://github.com/gocept/gocept.patch_keyreferences
Author: gocept gmbh & co. kg
Author-email: mail@gocept.com
License: MIT
Keywords: zodb zope reference fix
Platform: UNKNOWN
Classifier: Topic :: Software Development
Classifier: Topic :: Database
Classifier: Framework :: ZODB
Classifier: Framework :: Zope3
Classifier: Development Status :: 4 - Beta
Classifier: Intended Audience :: Developers
Classifier: License :: OSI Approved
Classifier: Programming Language :: Python :: 2
Classifier: Programming Language :: Python :: 2.7
Classifier: Programming Language :: Python :: 3
Classifier: Programming Language :: Python :: 3.6
Classifier: Programming Language :: Python :: 3.7
Classifier: Programming Language :: Python :: 3.8
Classifier: License :: OSI Approved :: MIT License
Classifier: Natural Language :: English
Classifier: Operating System :: OS Independent
Classifier: Programming Language :: Python
Requires-Dist: ZODB
Requires-Dist: collective.monkeypatcher
Requires-Dist: zope.security
Provides-Extra: test
Requires-Dist: zope.app.catalog[test] ; extra == 'test'
